pystencils_walberla/__init__.py
pystencils_walberla/cmake_integration.py
pystencils_walberla/codegen.py
pystencils_walberla/jinja_filters.py
pystencils_walberla/templates/CpuPackInfo.tmpl.cpp
pystencils_walberla/templates/CpuPackInfo.tmpl.h
pystencils_walberla/templates/GpuPackInfo.tmpl.cpp
pystencils_walberla/templates/GpuPackInfo.tmpl.h
pystencils_walberla/templates/MpiDtypeInfo.tmpl.h
pystencils_walberla/templates/Sweep.tmpl.cpp
pystencils_walberla/templates/Sweep.tmpl.h
pystencils_walberla/templates/SweepInnerOuter.tmpl.cpp
pystencils_walberla/templates/SweepInnerOuter.tmpl.h
pystencils_walberla-0.2.5.dist-info/COPYING.txt
pystencils_walberla-0.2.5.dist-info/METADATA
pystencils_walberla-0.2.5.dist-info/WHEEL
pystencils_walberla-0.2.5.dist-info/top_level.txt
pystencils_walberla-0.2.5.dist-info/RECORD
